muguobox/paper_prompt_finetune/__init__.py
muguobox/paper_prompt_finetune/settings.py
muguobox/paper_prompt_finetune/utils.py
muguobox_paper_prompt_finetune-0.0.1.dist-info/METADATA
muguobox_paper_prompt_finetune-0.0.1.dist-info/WHEEL
muguobox_paper_prompt_finetune-0.0.1.dist-info/top_level.txt
muguobox_paper_prompt_finetune-0.0.1.dist-info/RECORD
