Metadata-Version: 2.1
Name: muguobox-paper-prompt-finetune
Version: 0.0.1
Summary: A muguo toolkit for finetuning AIGC prompts
Requires-Dist: snqueue
Requires-Dist: pydantic-settings
Requires-Dist: mediqbox-download
Requires-Dist: mediqbox-gptchat
